isomode/__init__.py
isomode/anamode.py
isomode/domain.py
isomode/frozen_mode.py
isomode/gen_all.py
isomode/isodistort_parser.py
isomode/perovskite_mode.py
isomode/phonmode.py
isomode/pydistort.py
isomode/symbol.py
isomode/extern/__init__.py
isomode/extern/cells.py
isomode-0.3.4.dist-info/METADATA
isomode-0.3.4.dist-info/WHEEL
isomode-0.3.4.dist-info/entry_points.txt
isomode-0.3.4.dist-info/licenses/LICENSE
isomode-0.3.4.dist-info/RECORD
