Metadata-Version: 2.4
Name: isomode
Version: 0.3.4
Summary: Label/generate distorted structure from phonon/isodistort output
Author-email: Xu He <mailhexu@gmail.com>
License: MIT
License-File: LICENSE
Classifier: Development Status :: 3 - Alpha
Requires-Dist: abipy==0.9.8
Requires-Dist: ase
Requires-Dist: bs4
Requires-Dist: lxml
Requires-Dist: numpy==1.26.4
Requires-Dist: pymatgen==2025.4.20
Requires-Dist: requests
Requires-Dist: scipy<=1.16
Requires-Dist: spglib
